[{"Product/Internal Reference":"18009501","Product/Name":"Neutrogena Retinol Boost Day Cream SPF 15 (50ml)","Product/Barcode":"3574661657394","Financial Category":"Personal Care 2","Available Quantity":4.0,"Quantity":4.0,"Location":"KAT/Stock/Zone (E)/Line 16/ZE-16-A09","Lot/Serial Number/Production Date":"2023-05-01 00:00:00","Lot/Serial Number/Expiration Date":"2026-04-30 00:00:00","Lot/Serial Number/Removal Date":"2026-01-10 23:00:00","Lot/Serial Number/Alert Date":"2026-04-30 00:00:00"},{"Product/Internal Reference":"10053798","Product/Name":"Nivea Sun Intense Bronze Tanning Sun Lotion, Vitamin E, SPF 6 (200ml)","Product/Barcode":"4005900277862","Financial Category":"Personal Care 2","Available Quantity":1.0,"Quantity":1.0,"Location":"KAT/Stock/Zone (E)/Line 16/ZE-16-C01","Lot/Serial Number/Production Date":"2024-11-01 15:00:00","Lot/Serial Number/Expiration Date":"2027-11-01 15:00:00","Lot/Serial Number/Removal Date":"2027-07-15 16:00:00","Lot/Serial Number/Alert Date":"2027-04-11 15:00:00"},{"Product/Internal Reference":"11074094","Product/Name":"Nivea Fresh Natural Deodorant For Women Ocean Extracts Stick (50ml)","Product/Barcode":"4005900908131","Financial Category":"Personal Care 2","Available Quantity":5.0,"Quantity":5.0,"Location":"KAT/Stock/Zone (E)/Line 16/ZE-16-C01","Lot/Serial Number/Production Date":"2024-02-01 16:00:00","Lot/Serial Number/Expiration Date":"2026-07-20 17:00:00","Lot/Serial Number/Removal Date":"2026-04-21 16:00:00","Lot/Serial Number/Alert Date":"2026-07-20 17:00:00"},{"Product/Internal Reference":"1380847","Product/Name":"Nivea Micellair Water Make-Up Remover For All Skin Type (400ml)","Product/Barcode":"4005900339263","Financial Category":"Personal Care 2","Available Quantity":1.0,"Quantity":1.0,"Location":"KAT/Stock/Zone (E)/Line 16/ZE-16-C01","Lot/Serial Number/Production Date":"2024-03-01 00:00:00","Lot/Serial Number/Expiration Date":"2026-08-28 01:00:00","Lot/Serial Number/Removal Date":"2026-05-29 01:00:00","Lot/Serial Number/Alert Date":"2026-08-28 01:00:00"},{"Product/Internal Reference":"1380847","Product/Name":"Nivea Micellair Water Make-Up Remover For All Skin Type (400ml)","Product/Barcode":"4005900339263","Financial Category":"Personal Care 2","Available Quantity":5.0,"Quantity":5.0,"Location":"KAT/Stock/Zone (E)/Line 16/ZE-16-C01","Lot/Serial Number/Production Date":"2024-05-01 15:00:00","Lot/Serial Number/Expiration Date":"2026-10-28 15:00:00","Lot/Serial Number/Removal Date":"2026-07-29 15:00:00","Lot/Serial Number/Alert Date":"2026-10-28 15:00:00"}]