[{"Product/Internal Reference":"1138370","Product/Name":"Almarai Natural Yogurt Offer 5+1 Free (105g)","Product/Barcode":"6223001875482","Financial Category":"Yogurt","Available Quantity":0.0,"Quantity":0.0,"Location":"KAT/Stock","Lot/Serial Number/Production Date":"2025-07-14 10:00:00","Lot/Serial Number/Expiration Date":"2025-08-13 10:00:00","Lot/Serial Number/Removal Date":"2025-08-01 10:00:00","Lot/Serial Number/Alert Date":"2025-08-13 10:00:00"},{"Product/Internal Reference":"23178706","Product/Name":"Dolato Minis Premium Mixed Box (25 pcs)","Product/Barcode":"","Financial Category":"Frozen Desserts and Ice Cream","Available Quantity":48.0,"Quantity":48.0,"Location":"KAT/Stock","Lot/Serial Number/Production Date":"2025-07-11 16:00:00","Lot/Serial Number/Expiration Date":"2026-01-07 15:00:00","Lot/Serial Number/Removal Date":"2025-12-20 15:00:00","Lot/Serial Number/Alert Date":"2026-01-07 15:00:00"},{"Product/Internal Reference":"23178711","Product/Name":"Dolato Minis Special Mixed Box (25 pcs)","Product/Barcode":"","Financial Category":"Frozen Desserts and Ice Cream","Available Quantity":384.0,"Quantity":384.0,"Location":"KAT/Stock","Lot/Serial Number/Production Date":"2025-07-11 16:00:00","Lot/Serial Number/Expiration Date":"2026-01-09 15:00:00","Lot/Serial Number/Removal Date":"2025-12-21 15:00:00","Lot/Serial Number/Alert Date":"2026-01-09 15:00:00"},{"Product/Internal Reference":"33184556","Product/Name":"Lychee Real Orange Juice with pulp (350ml)","Product/Barcode":"","Financial Category":"Centralized Fresh","Available Quantity":0.0,"Quantity":0.0,"Location":"KAT/Stock","Lot/Serial Number/Production Date":"2025-07-14 17:00:00","Lot/Serial Number/Expiration Date":"2025-08-03 17:00:00","Lot/Serial Number/Removal Date":"2025-07-26 17:00:00","Lot/Serial Number/Alert Date":"2025-08-03 17:00:00"},{"Product/Internal Reference":"7789424","Product/Name":"Abu Auf French Coffee (250g)","Product/Barcode":"6223004765285","Financial Category":"Coffee & Other Drinks","Available Quantity":2.0,"Quantity":2.0,"Location":"KAT/Stock","Lot/Serial Number/Production Date":"2025-06-01 13:00:00","Lot/Serial Number/Expiration Date":"2027-06-01 13:00:00","Lot/Serial Number/Removal Date":"2027-02-21 12:00:00","Lot/Serial Number/Alert Date":"2027-06-01 13:00:00"}]