[{"Product/Internal Reference":"8584360","Product/Name":"Almarai Full Cream Milk Plastic (1.5L)","Product/Barcode":"6223001878018","Financial Category":"Milk","Available Quantity":384.0,"Quantity":384.0,"Location":"KAT/Stock/Zone (C)/Line 10/ZC-10-E15","Lot/Serial Number/Production Date":"2025-06-11 18:00:00","Lot/Serial Number/Expiration Date":"2025-12-08 17:00:00","Lot/Serial Number/Removal Date":"2025-11-20 17:00:00","Lot/Serial Number/Alert Date":"2025-12-08 17:00:00"},{"Product/Internal Reference":"8584360","Product/Name":"Almarai Full Cream Milk Plastic (1.5L)","Product/Barcode":"6223001878018","Financial Category":"Milk","Available Quantity":384.0,"Quantity":384.0,"Location":"KAT/Stock/Zone (C)/Line 10/ZC-10-C16","Lot/Serial Number/Production Date":"2025-06-11 18:00:00","Lot/Serial Number/Expiration Date":"2025-12-08 17:00:00","Lot/Serial Number/Removal Date":"2025-11-20 17:00:00","Lot/Serial Number/Alert Date":"2025-12-08 17:00:00"},{"Product/Internal Reference":"8584360","Product/Name":"Almarai Full Cream Milk Plastic (1.5L)","Product/Barcode":"6223001878018","Financial Category":"Milk","Available Quantity":384.0,"Quantity":384.0,"Location":"KAT/Stock/Zone (C)/Line 10/ZC-10-D16","Lot/Serial Number/Production Date":"2025-06-11 18:00:00","Lot/Serial Number/Expiration Date":"2025-12-08 17:00:00","Lot/Serial Number/Removal Date":"2025-11-20 17:00:00","Lot/Serial Number/Alert Date":"2025-12-08 17:00:00"},{"Product/Internal Reference":"8584360","Product/Name":"Almarai Full Cream Milk Plastic (1.5L)","Product/Barcode":"6223001878018","Financial Category":"Milk","Available Quantity":384.0,"Quantity":384.0,"Location":"KAT/Stock/Zone (C)/Line 10/ZC-10-E16","Lot/Serial Number/Production Date":"2025-06-11 18:00:00","Lot/Serial Number/Expiration Date":"2025-12-08 17:00:00","Lot/Serial Number/Removal Date":"2025-11-20 17:00:00","Lot/Serial Number/Alert Date":"2025-12-08 17:00:00"},{"Product/Internal Reference":"8584360","Product/Name":"Almarai Full Cream Milk Plastic (1.5L)","Product/Barcode":"6223001878018","Financial Category":"Milk","Available Quantity":8.0,"Quantity":8.0,"Location":"KAT/Stock/Zone (C)/Line 10/ZC-10-A19","Lot/Serial Number/Production Date":"2025-06-11 18:00:00","Lot/Serial Number/Expiration Date":"2025-12-08 17:00:00","Lot/Serial Number/Removal Date":"2025-11-20 17:00:00","Lot/Serial Number/Alert Date":"2025-12-08 17:00:00"}]