[{"Product/Internal Reference":"33897701","Product/Name":"Daria Basmati Rice Gold (2 kg)","Product/Barcode":"","Financial Category":"Food Cupboard 2","Available Quantity":1.0,"Quantity":1.0,"Location":"KAT/Stock/Zone (E)/Line 12/ZE-12-C09","Lot/Serial Number/Production Date":"2025-01-01 13:00:00","Lot/Serial Number/Expiration Date":"2027-01-01 13:00:00","Lot/Serial Number/Removal Date":"2026-10-20 14:00:00","Lot/Serial Number/Alert Date":"2027-01-01 13:00:00"},{"Product/Internal Reference":"37228138","Product/Name":"Naturesta Puree Tomato Herbs And Garlic (210g)","Product/Barcode":"","Financial Category":"Food Cupboard 2","Available Quantity":47.0,"Quantity":47.0,"Location":"KAT/Stock/Zone (D)/Line 13/ZD-13-B02","Lot/Serial Number/Production Date":"2025-01-30 15:00:00","Lot/Serial Number/Expiration Date":"2026-01-30 15:00:00","Lot/Serial Number/Removal Date":"2026-01-30 15:00:00","Lot/Serial Number/Alert Date":"2026-01-30 15:00:00"},{"Product/Internal Reference":"31123178","Product/Name":"Hohos Uncoated Chocolate Family Cake (210g)","Product/Barcode":"6223000556337","Financial Category":"Snacks","Available Quantity":126.0,"Quantity":126.0,"Location":"KAT/Stock/Zone (D)/Line 08/ZD-08-C10","Lot/Serial Number/Production Date":"2025-06-16 11:00:00","Lot/Serial Number/Expiration Date":"2025-08-15 11:00:00","Lot/Serial Number/Removal Date":"2025-08-03 11:00:00","Lot/Serial Number/Alert Date":"2025-08-15 11:00:00"},{"Product/Internal Reference":"22880964","Product/Name":"Hohos Cream King Size (Piece)","Product/Barcode":"6223000555118","Financial Category":"Snacks","Available Quantity":0.0,"Quantity":0.0,"Location":"KAT/Stock/Zone (D)/Line 08/ZD-08-C08","Lot/Serial Number/Production Date":"2025-06-28 11:00:00","Lot/Serial Number/Expiration Date":"2025-09-26 11:00:00","Lot/Serial Number/Removal Date":"2025-09-08 11:00:00","Lot/Serial Number/Alert Date":"2025-09-26 11:00:00"},{"Product/Internal Reference":"25380220","Product/Name":"Hohos Cream King Size 12Pcs (Box)","Product/Barcode":"","Financial Category":"Snacks","Available Quantity":0.0,"Quantity":0.0,"Location":"KAT/Stock/Zone (D)/Line 08/ZD-08-A08","Lot/Serial Number/Production Date":"2025-06-28 11:00:00","Lot/Serial Number/Expiration Date":"2025-09-26 11:00:00","Lot/Serial Number/Removal Date":"2025-09-08 11:00:00","Lot/Serial Number/Alert Date":"2025-09-26 11:00:00"}]