[{"Product/Internal Reference":"37994491","Product/Name":"B Laban Chookies (8 Pieces)","Product/Barcode":"","Financial Category":"Snacks","Available Quantity":194.0,"Quantity":194.0,"Location":"KAT/Stock/Zone (D)/Line 04/ZD-04-C06","Lot/Serial Number/Production Date":"2025-06-30 11:00:00","Lot/Serial Number/Expiration Date":"2026-06-30 11:00:00","Lot/Serial Number/Removal Date":"2026-06-30 11:00:00","Lot/Serial Number/Alert Date":"2026-06-30 11:00:00"},{"Product/Internal Reference":"37994491","Product/Name":"B Laban Chookies (8 Pieces)","Product/Barcode":"","Financial Category":"Snacks","Available Quantity":144.0,"Quantity":144.0,"Location":"KAT/Stock/Zone (D)/Line 04/ZD-04-B06","Lot/Serial Number/Production Date":"2025-06-30 11:00:00","Lot/Serial Number/Expiration Date":"2026-06-30 11:00:00","Lot/Serial Number/Removal Date":"2026-06-30 11:00:00","Lot/Serial Number/Alert Date":"2026-06-30 11:00:00"},{"Product/Internal Reference":"35581954","Product/Name":"B Laban Hazelnut Chocolate Spread Cream (500g)","Product/Barcode":"","Financial Category":"Food Cupboard 2","Available Quantity":288.0,"Quantity":288.0,"Location":"KAT/Stock/Zone (E)/Line 10/ZE-10-C02","Lot/Serial Number/Production Date":"2025-07-01 12:00:00","Lot/Serial Number/Expiration Date":"2026-07-01 12:00:00","Lot/Serial Number/Removal Date":"2026-07-01 12:00:00","Lot/Serial Number/Alert Date":"2026-07-01 12:00:00"},{"Product/Internal Reference":"35581954","Product/Name":"B Laban Hazelnut Chocolate Spread Cream (500g)","Product/Barcode":"","Financial Category":"Food Cupboard 2","Available Quantity":66.0,"Quantity":66.0,"Location":"KAT/Stock/Zone (E)/Line 10/ZE-10-A02","Lot/Serial Number/Production Date":"2025-07-01 12:00:00","Lot/Serial Number/Expiration Date":"2026-07-01 12:00:00","Lot/Serial Number/Removal Date":"2026-07-01 12:00:00","Lot/Serial Number/Alert Date":"2026-07-01 12:00:00"},{"Product/Internal Reference":"14344049","Product/Name":"Familia Anti Bacterial Protection Facial Tissues 2 Ply Pack Of 6 (500Tissues)","Product/Barcode":"6223007652254","Financial Category":"Tissues","Available Quantity":0.0,"Quantity":0.0,"Location":"KAT/Stock/Zone (A)/Line 16/ZA-16-C06","Lot/Serial Number/Production Date":"2025-07-14 14:00:00","Lot/Serial Number/Expiration Date":"2039-03-23 13:00:00","Lot/Serial Number/Removal Date":"2037-11-08 13:00:00","Lot/Serial Number/Alert Date":"2039-03-23 13:00:00"}]