[{"Product/Internal Reference":"19350199","Product/Name":"Al Sonbolah Green Beans (400g)","Product/Barcode":"6281073150364","Financial Category":"Frozen Starters, cheese & FV","Available Quantity":280.0,"Quantity":280.0,"Location":"KAT/Stock","Lot/Serial Number/Production Date":"2025-01-01 15:00:00","Lot/Serial Number/Expiration Date":"2026-06-25 16:00:00","Lot/Serial Number/Removal Date":"2026-05-07 16:00:00","Lot/Serial Number/Alert Date":"2026-06-25 16:00:00"},{"Product/Internal Reference":"27281379","Product/Name":"Al Sonbolah Puff Pastry Square (400g)","Product/Barcode":"","Financial Category":"Frozen Starters, cheese & FV","Available Quantity":12.0,"Quantity":12.0,"Location":"KAT/Stock","Lot/Serial Number/Production Date":"2025-06-03 15:00:00","Lot/Serial Number/Expiration Date":"2025-11-30 14:00:00","Lot/Serial Number/Removal Date":"2026-10-07 15:00:00","Lot/Serial Number/Alert Date":"2025-11-30 14:00:00"},{"Product/Internal Reference":"2808617","Product/Name":"Al Sonbolah Molokhya (400g)","Product/Barcode":"6281073150869","Financial Category":"Frozen Starters, cheese & FV","Available Quantity":940.0,"Quantity":940.0,"Location":"KAT/Stock","Lot/Serial Number/Production Date":"2025-05-01 15:00:00","Lot/Serial Number/Expiration Date":"2026-10-23 15:00:00","Lot/Serial Number/Removal Date":"2026-10-23 15:00:00","Lot/Serial Number/Alert Date":"2026-10-23 15:00:00"},{"Product/Internal Reference":"9116019","Product/Name":"Hero Baby 2 Nutradefense Plus Infant Formula Milk From 6-12 Months (400g)","Product/Barcode":"8410175080127","Financial Category":"Milk","Available Quantity":9.0,"Quantity":9.0,"Location":"KAT/Stock","Lot/Serial Number/Production Date":"2024-05-03 08:00:00","Lot/Serial Number/Expiration Date":"2026-05-03 08:00:00","Lot/Serial Number/Removal Date":"2026-02-19 07:00:00","Lot/Serial Number/Alert Date":"2026-05-03 08:00:00"},{"Product/Internal Reference":"9562451","Product/Name":"Nutella B-Ready Wafer 6 Pcs *(132g)","Product/Barcode":"8000500227848","Financial Category":"Snacks","Available Quantity":8.0,"Quantity":8.0,"Location":"KAT/Stock","Lot/Serial Number/Production Date":"2025-02-24 12:00:00","Lot/Serial Number/Expiration Date":"2025-11-21 12:00:00","Lot/Serial Number/Removal Date":"2025-10-25 13:00:00","Lot/Serial Number/Alert Date":"2025-11-21 12:00:00"}]