[{"Product/Internal Reference":"14224007","Product/Name":"Fine Baby Diapers Size 5 Maxi 11-18 kg (58Diapers)","Product/Barcode":"6294018803997","Financial Category":"Personal Care","Available Quantity":0.0,"Quantity":0.0,"Location":"KAT/Stock/Zone (A)/Line 28/ZA-28-A14","Lot/Serial Number/Production Date":"2025-06-13 10:00:00","Lot/Serial Number/Expiration Date":"2028-06-12 10:00:00","Lot/Serial Number/Removal Date":"2028-02-24 09:00:00","Lot/Serial Number/Alert Date":"2028-06-12 10:00:00"},{"Product/Internal Reference":"1346320","Product/Name":"Haribo Happy Cola Gummi Candy (30g)","Product/Barcode":"8691216094321","Financial Category":"Snacks","Available Quantity":8.0,"Quantity":8.0,"Location":"KAT/Stock/Zone (D)/Line 01/ZD-01-C05","Lot/Serial Number/Production Date":"2024-11-29 14:00:00","Lot/Serial Number/Expiration Date":"2026-05-23 15:00:00","Lot/Serial Number/Removal Date":"2026-04-04 14:00:00","Lot/Serial Number/Alert Date":"2026-05-23 15:00:00"},{"Product/Internal Reference":"13548570","Product/Name":"Molfix Baby Diaper Pants Extra-large Size 6 (64diapers)","Product/Barcode":"6223006344815","Financial Category":"Personal Care","Available Quantity":60.0,"Quantity":60.0,"Location":"KAT/Stock/Zone (A)/Line 31/ZA-31-D09","Lot/Serial Number/Production Date":"2025-07-06 11:00:00","Lot/Serial Number/Expiration Date":"2028-07-05 11:00:00","Lot/Serial Number/Removal Date":"2028-03-18 10:00:00","Lot/Serial Number/Alert Date":"2028-07-05 11:00:00"},{"Product/Internal Reference":"13548570","Product/Name":"Molfix Baby Diaper Pants Extra-large Size 6 (64diapers)","Product/Barcode":"6223006344815","Financial Category":"Personal Care","Available Quantity":60.0,"Quantity":60.0,"Location":"KAT/Stock/Zone (A)/Line 31/ZA-31-C08","Lot/Serial Number/Production Date":"2025-07-06 11:00:00","Lot/Serial Number/Expiration Date":"2028-07-05 11:00:00","Lot/Serial Number/Removal Date":"2028-03-18 10:00:00","Lot/Serial Number/Alert Date":"2028-07-05 11:00:00"},{"Product/Internal Reference":"13548570","Product/Name":"Molfix Baby Diaper Pants Extra-large Size 6 (64diapers)","Product/Barcode":"6223006344815","Financial Category":"Personal Care","Available Quantity":60.0,"Quantity":60.0,"Location":"KAT/Stock/Zone (A)/Line 31/ZA-31-C16","Lot/Serial Number/Production Date":"2025-07-06 11:00:00","Lot/Serial Number/Expiration Date":"2028-07-05 11:00:00","Lot/Serial Number/Removal Date":"2028-03-18 10:00:00","Lot/Serial Number/Alert Date":"2028-07-05 11:00:00"}]