[{"Product/Internal Reference":"22828462","Product/Name":"White Flexi 3 Ply Pack of 3 (500Tissues)","Product/Barcode":"6224011512800","Financial Category":"Tissues","Available Quantity":324.0,"Quantity":324.0,"Location":"KAT/Stock/Zone (A)/Line 16/ZA-16-C03","Lot/Serial Number/Production Date":"2025-07-10 11:00:00","Lot/Serial Number/Expiration Date":"2028-07-09 11:00:00","Lot/Serial Number/Removal Date":"2028-03-22 10:00:00","Lot/Serial Number/Alert Date":"2028-07-09 11:00:00"},{"Product/Internal Reference":"22828462","Product/Name":"White Flexi 3 Ply Pack of 3 (500Tissues)","Product/Barcode":"6224011512800","Financial Category":"Tissues","Available Quantity":360.0,"Quantity":360.0,"Location":"KAT/Stock/Zone (A)/Line 17/ZA-17-C10","Lot/Serial Number/Production Date":"2025-07-10 11:00:00","Lot/Serial Number/Expiration Date":"2028-07-09 11:00:00","Lot/Serial Number/Removal Date":"2028-03-22 10:00:00","Lot/Serial Number/Alert Date":"2028-07-09 11:00:00"},{"Product/Internal Reference":"5131774","Product/Name":"White Chef Kitchen Classic Towel 5+1 Free (6 Rolls)","Product/Barcode":"6224007860625","Financial Category":"Tissues","Available Quantity":0.0,"Quantity":0.0,"Location":"KAT/Stock/Zone (A)/Line 17/ZA-17-B02","Lot/Serial Number/Production Date":"2025-07-10 10:00:00","Lot/Serial Number/Expiration Date":"2039-03-19 09:00:00","Lot/Serial Number/Removal Date":"2037-11-04 09:00:00","Lot/Serial Number/Alert Date":"2026-11-22 09:00:00"},{"Product/Internal Reference":"5131774","Product/Name":"White Chef Kitchen Classic Towel 5+1 Free (6 Rolls)","Product/Barcode":"6224007860625","Financial Category":"Tissues","Available Quantity":0.0,"Quantity":0.0,"Location":"KAT/Stock/Zone (A)/Line 17/ZA-17-B03","Lot/Serial Number/Production Date":"2025-07-10 10:00:00","Lot/Serial Number/Expiration Date":"2039-03-19 09:00:00","Lot/Serial Number/Removal Date":"2037-11-04 09:00:00","Lot/Serial Number/Alert Date":"2026-11-22 09:00:00"},{"Product/Internal Reference":"5131774","Product/Name":"White Chef Kitchen Classic Towel 5+1 Free (6 Rolls)","Product/Barcode":"6224007860625","Financial Category":"Tissues","Available Quantity":0.0,"Quantity":0.0,"Location":"KAT/Stock/Zone (A)/Line 17/ZA-17-B04","Lot/Serial Number/Production Date":"2025-07-10 10:00:00","Lot/Serial Number/Expiration Date":"2039-03-19 09:00:00","Lot/Serial Number/Removal Date":"2037-11-04 09:00:00","Lot/Serial Number/Alert Date":"2026-11-22 09:00:00"}]