[{"Product/Internal Reference":"8564644","Product/Name":"Sun Top Berry Mix Juice (250ml)","Product/Barcode":"6224000490836","Financial Category":"Juice","Available Quantity":360.0,"Quantity":360.0,"Location":"KAT/Stock/Zone (C)/Line 04/ZC-04-A01","Lot/Serial Number/Production Date":"2025-06-12 11:00:00","Lot/Serial Number/Expiration Date":"2026-06-12 11:00:00","Lot/Serial Number/Removal Date":"2026-05-07 11:00:00","Lot/Serial Number/Alert Date":"2026-06-12 11:00:00"},{"Product/Internal Reference":"8563242","Product/Name":"Sun Top Apple Juice (250ml)","Product/Barcode":"6224010950146","Financial Category":"Juice","Available Quantity":240.0,"Quantity":240.0,"Location":"KAT/Stock/Zone (C)/Line 04/ZC-04-A02","Lot/Serial Number/Production Date":"2025-06-30 11:00:00","Lot/Serial Number/Expiration Date":"2026-06-30 11:00:00","Lot/Serial Number/Removal Date":"2026-05-25 11:00:00","Lot/Serial Number/Alert Date":"2026-06-30 11:00:00"},{"Product/Internal Reference":"8563975","Product/Name":"Sun Top Guava Juice (250ml)","Product/Barcode":"6224010950139","Financial Category":"Juice","Available Quantity":384.0,"Quantity":384.0,"Location":"KAT/Stock/Zone (C)/Line 04/ZC-04-A02","Lot/Serial Number/Production Date":"2025-07-16 10:00:00","Lot/Serial Number/Expiration Date":"2026-07-15 10:00:00","Lot/Serial Number/Removal Date":"2026-06-09 10:00:00","Lot/Serial Number/Alert Date":"2026-07-15 10:00:00"},{"Product/Internal Reference":"29003833","Product/Name":"Sun Top Pink Lemonade Juice (250ml)","Product/Barcode":"","Financial Category":"Juice","Available Quantity":312.0,"Quantity":312.0,"Location":"KAT/Stock/Zone (C)/Line 04/ZC-04-A02","Lot/Serial Number/Production Date":"2025-05-24 10:00:00","Lot/Serial Number/Expiration Date":"2026-05-24 10:00:00","Lot/Serial Number/Removal Date":"2026-04-18 09:00:00","Lot/Serial Number/Alert Date":"2026-05-24 10:00:00"},{"Product/Internal Reference":"37635063","Product/Name":"Sun Top Spicy Tangerine (250ml)","Product/Barcode":"","Financial Category":"Juice","Available Quantity":672.0,"Quantity":672.0,"Location":"KAT/Stock/Zone (C)/Line 04/ZC-04-A02","Lot/Serial Number/Production Date":"2025-06-23 10:00:00","Lot/Serial Number/Expiration Date":"2026-06-23 10:00:00","Lot/Serial Number/Removal Date":"2026-06-23 10:00:00","Lot/Serial Number/Alert Date":"2026-06-23 10:00:00"}]