[{"Product/Internal Reference":"1900647","Product/Name":"Fine Super Paper Towel Multipurpose 2 Ply (5+1 Rolls)","Product/Barcode":"6251001220575","Financial Category":"Tissues","Available Quantity":8.0,"Quantity":8.0,"Location":"KAT/Stock/Zone (A)/Line 26/ZA-26-C16","Lot/Serial Number/Production Date":"2025-06-27 10:00:00","Lot/Serial Number/Expiration Date":"2030-06-26 10:00:00","Lot/Serial Number/Removal Date":"2029-12-26 09:00:00","Lot/Serial Number/Alert Date":"2027-04-01 09:00:00"},{"Product/Internal Reference":"1003444","Product/Name":"Schweppes Tonic Water Glass Bottle (250ml)","Product/Barcode":"90492907","Financial Category":"Soda","Available Quantity":0.0,"Quantity":0.0,"Location":"KAT/Stock/Zone (C)/Line 01/ZC-01-A10","Lot/Serial Number/Production Date":"2025-07-13 17:00:00","Lot/Serial Number/Expiration Date":"2026-07-13 17:00:00","Lot/Serial Number/Removal Date":"2026-06-07 17:00:00","Lot/Serial Number/Alert Date":"2026-07-13 17:00:00"},{"Product/Internal Reference":"9046591","Product/Name":"Fayrouz Pineapple Bottle (275ml)","Product/Barcode":"6223000084021","Financial Category":"Soda","Available Quantity":0.0,"Quantity":0.0,"Location":"KAT/Stock/Zone (C)/Line 01/ZC-01-A10","Lot/Serial Number/Production Date":"2025-07-11 14:00:00","Lot/Serial Number/Expiration Date":"2026-07-11 14:00:00","Lot/Serial Number/Removal Date":"2026-06-05 14:00:00","Lot/Serial Number/Alert Date":"2026-07-11 14:00:00"},{"Product/Internal Reference":"3170346","Product/Name":"El Hanim Vegetable Ghee (350g)","Product/Barcode":"6222000552455","Financial Category":"Commodities","Available Quantity":20.0,"Quantity":20.0,"Location":"KAT/Stock/Zone (B)/Line 02/ZB-02-A07","Lot/Serial Number/Production Date":"2025-01-05 00:00:00","Lot/Serial Number/Expiration Date":"2027-01-05 00:00:00","Lot/Serial Number/Removal Date":"2026-10-24 01:00:00","Lot/Serial Number/Alert Date":"2027-01-05 00:00:00"},{"Product/Internal Reference":"1900647","Product/Name":"Fine Super Paper Towel Multipurpose 2 Ply (5+1 Rolls)","Product/Barcode":"6251001220575","Financial Category":"Tissues","Available Quantity":16.0,"Quantity":16.0,"Location":"KAT/Stock/Zone (A)/Line 22/ZA-22-A08","Lot/Serial Number/Production Date":"2025-06-27 10:00:00","Lot/Serial Number/Expiration Date":"2030-06-26 10:00:00","Lot/Serial Number/Removal Date":"2029-12-26 09:00:00","Lot/Serial Number/Alert Date":"2027-04-01 09:00:00"}]