[{"Product/Internal Reference":"31943526","Product/Name":"Clear Shampoo Anti Hair Fall (600ml)","Product/Barcode":"","Financial Category":"Personal Care","Available Quantity":6.0,"Quantity":6.0,"Location":"KAT/Stock/Zone (A)/Line 29/ZA-29-A09","Lot/Serial Number/Production Date":"2025-01-16 14:00:00","Lot/Serial Number/Expiration Date":"2028-01-16 14:00:00","Lot/Serial Number/Removal Date":"2028-01-16 14:00:00","Lot/Serial Number/Alert Date":"2028-01-16 14:00:00"},{"Product/Internal Reference":"36836754","Product/Name":"Lord Nebty 3 Blade Razor Refills – 4 Cartridges for Daily Shaving","Product/Barcode":"","Financial Category":"Personal Care","Available Quantity":4.0,"Quantity":4.0,"Location":"KAT/Stock/Zone (A)/Line 29/ZA-29-A16","Lot/Serial Number/Production Date":"2025-06-01 00:00:00","Lot/Serial Number/Expiration Date":"2028-05-31 00:00:00","Lot/Serial Number/Removal Date":"2028-05-31 00:00:00","Lot/Serial Number/Alert Date":"2028-05-31 00:00:00"},{"Product/Internal Reference":"36836752","Product/Name":"Lord Horus 5 Blade Razor Refills – 4 Cartridges for Smooth, Close Shave","Product/Barcode":"","Financial Category":"Personal Care","Available Quantity":4.0,"Quantity":4.0,"Location":"KAT/Stock/Zone (A)/Line 29/ZA-29-A16","Lot/Serial Number/Production Date":"2025-06-01 00:00:00","Lot/Serial Number/Expiration Date":"2028-05-31 00:00:00","Lot/Serial Number/Removal Date":"2028-05-31 00:00:00","Lot/Serial Number/Alert Date":"2028-05-31 00:00:00"},{"Product/Internal Reference":"34852648","Product/Name":"Infinity Naturals Body Lotion – Strawberry Extract (250ml)","Product/Barcode":"","Financial Category":"Personal Care","Available Quantity":1.0,"Quantity":1.0,"Location":"KAT/Stock/Zone (A)/Line 30/ZA-30-A05","Lot/Serial Number/Production Date":"2025-03-01 15:00:00","Lot/Serial Number/Expiration Date":"2028-02-29 15:00:00","Lot/Serial Number/Removal Date":"2028-02-29 15:00:00","Lot/Serial Number/Alert Date":"2028-02-29 15:00:00"},{"Product/Internal Reference":"3634920","Product/Name":"Clear Shampoo Soft & Shiny For Women Special Offer 10LE (360ml)","Product/Barcode":"6221155060716","Financial Category":"Personal Care 2","Available Quantity":2.0,"Quantity":2.0,"Location":"KAT/Stock/Zone (E)/Line 16/ZE-16-A04","Lot/Serial Number/Production Date":"2024-01-09 00:00:00","Lot/Serial Number/Expiration Date":"2027-01-08 00:00:00","Lot/Serial Number/Removal Date":"2026-09-21 01:00:00","Lot/Serial Number/Alert Date":"2027-01-08 00:00:00"}]