[{"Product/Internal Reference":"34986668","Product/Name":"Tiger Chili and Lemon (53-63g)","Product/Barcode":"","Financial Category":"Food","Available Quantity":825.0,"Quantity":825.0,"Location":"KAT/Stock/Zone (F)/Line 17/ZF-17-C11","Lot/Serial Number/Production Date":"2025-07-15 14:00:00","Lot/Serial Number/Expiration Date":"2026-01-11 13:00:00","Lot/Serial Number/Removal Date":"2025-12-24 13:00:00","Lot/Serial Number/Alert Date":"2026-01-11 13:00:00"},{"Product/Internal Reference":"4453837","Product/Name":"Breadfast Creamy Peanut Butter (330g)","Product/Barcode":"6221295004472","Financial Category":"Food Cupboard 2","Available Quantity":360.0,"Quantity":360.0,"Location":"KAT/Stock/Zone (C)/Line 11/ZC-11-B15","Lot/Serial Number/Production Date":"2025-07-14 13:00:00","Lot/Serial Number/Expiration Date":"2026-07-14 13:00:00","Lot/Serial Number/Removal Date":"2026-06-08 13:00:00","Lot/Serial Number/Alert Date":"2026-07-14 13:00:00"},{"Product/Internal Reference":"4453923","Product/Name":"Breadfast Creamy Chocolate Peanut Butter (330g)","Product/Barcode":"6221295004489","Financial Category":"Food Cupboard 2","Available Quantity":540.0,"Quantity":540.0,"Location":"KAT/Stock/Zone (E)/Line 10/ZE-10-B07","Lot/Serial Number/Production Date":"2025-07-14 13:00:00","Lot/Serial Number/Expiration Date":"2026-07-14 13:00:00","Lot/Serial Number/Removal Date":"2026-06-08 13:00:00","Lot/Serial Number/Alert Date":"2026-07-14 13:00:00"},{"Product/Internal Reference":"6201984","Product/Name":"Breadfast Tri-Colour Quinoa (400g)","Product/Barcode":"6224010265332","Financial Category":"Food Cupboard 2","Available Quantity":504.0,"Quantity":504.0,"Location":"KAT/Stock/Zone (E)/Line 10/ZE-10-C06","Lot/Serial Number/Production Date":"2025-07-16 13:00:00","Lot/Serial Number/Expiration Date":"2026-07-16 13:00:00","Lot/Serial Number/Removal Date":"2026-06-10 13:00:00","Lot/Serial Number/Alert Date":"2026-07-16 13:00:00"},{"Product/Internal Reference":"4453837","Product/Name":"Breadfast Creamy Peanut Butter (330g)","Product/Barcode":"6221295004472","Financial Category":"Food Cupboard 2","Available Quantity":936.0,"Quantity":936.0,"Location":"KAT/Stock/Zone (C)/Line 11/ZC-11-C15","Lot/Serial Number/Production Date":"2025-07-14 13:00:00","Lot/Serial Number/Expiration Date":"2026-07-14 13:00:00","Lot/Serial Number/Removal Date":"2026-06-08 13:00:00","Lot/Serial Number/Alert Date":"2026-07-14 13:00:00"}]