[{"Product/Internal Reference":"7562448","Product/Name":"Danette Caramel Mini Pudding (100g)","Product/Barcode":"6223002380145","Financial Category":"Yogurt","Available Quantity":192.0,"Quantity":192.0,"Location":"KAT/Stock","Lot/Serial Number/Production Date":"2025-07-23 11:00:00","Lot/Serial Number/Expiration Date":"2025-09-06 11:00:00","Lot/Serial Number/Removal Date":"2025-08-19 11:00:00","Lot/Serial Number/Alert Date":"2025-09-06 11:00:00"},{"Product/Internal Reference":"7562448","Product/Name":"Danette Caramel Mini Pudding (100g)","Product/Barcode":"6223002380145","Financial Category":"Yogurt","Available Quantity":43.0,"Quantity":43.0,"Location":"KAT/Stock","Lot/Serial Number/Production Date":"2025-07-22 11:00:00","Lot/Serial Number/Expiration Date":"2025-09-05 11:00:00","Lot/Serial Number/Removal Date":"2025-08-18 11:00:00","Lot/Serial Number/Alert Date":"2025-09-05 11:00:00"},{"Product/Internal Reference":"1180627","Product/Name":"Danette Chocolate Pudding (100g)","Product/Barcode":"6223002380152","Financial Category":"Yogurt","Available Quantity":912.0,"Quantity":912.0,"Location":"KAT/Stock","Lot/Serial Number/Production Date":"2025-07-23 11:00:00","Lot/Serial Number/Expiration Date":"2025-09-06 11:00:00","Lot/Serial Number/Removal Date":"2025-08-19 11:00:00","Lot/Serial Number/Alert Date":"2025-09-06 11:00:00"},{"Product/Internal Reference":"1180627","Product/Name":"Danette Chocolate Pudding (100g)","Product/Barcode":"6223002380152","Financial Category":"Yogurt","Available Quantity":96.0,"Quantity":96.0,"Location":"KAT/Stock","Lot/Serial Number/Production Date":"2025-07-22 11:00:00","Lot/Serial Number/Expiration Date":"2025-09-05 11:00:00","Lot/Serial Number/Removal Date":"2025-08-18 11:00:00","Lot/Serial Number/Alert Date":"2025-09-05 11:00:00"},{"Product/Internal Reference":"9255948","Product/Name":"Danette Vanilla Pudding (100g)","Product/Barcode":"6223002380343","Financial Category":"Yogurt","Available Quantity":0.0,"Quantity":0.0,"Location":"KAT/Stock","Lot/Serial Number/Production Date":"2025-07-19 11:00:00","Lot/Serial Number/Expiration Date":"2025-09-02 11:00:00","Lot/Serial Number/Removal Date":"2025-08-15 11:00:00","Lot/Serial Number/Alert Date":"2025-09-02 11:00:00"}]