[{"Product/Internal Reference":"33175058","Product/Name":"Rich Bake Bread Crumbs (200g)","Product/Barcode":"","Financial Category":"Food Cupboard 2","Available Quantity":120.0,"Quantity":120.0,"Location":"KAT/Stock/Zone (E)/Line 14/ZE-14-B01","Lot/Serial Number/Production Date":"2025-06-24 15:00:00","Lot/Serial Number/Expiration Date":"2026-03-21 14:00:00","Lot/Serial Number/Removal Date":"2026-02-22 14:00:00","Lot/Serial Number/Alert Date":"2026-03-21 14:00:00"},{"Product/Internal Reference":"31695540","Product/Name":"Elbawadi Halva Bar (18 gm)","Product/Barcode":"","Financial Category":"Food Cupboard 2","Available Quantity":408.0,"Quantity":408.0,"Location":"KAT/Stock/Zone (D)/Line 14/ZD-14-B06","Lot/Serial Number/Production Date":"2025-05-19 14:00:00","Lot/Serial Number/Expiration Date":"2026-05-19 14:00:00","Lot/Serial Number/Removal Date":"2026-04-13 13:00:00","Lot/Serial Number/Alert Date":"2026-05-19 14:00:00"},{"Product/Internal Reference":"31695540","Product/Name":"Elbawadi Halva Bar (18 gm)","Product/Barcode":"","Financial Category":"Food Cupboard 2","Available Quantity":120.0,"Quantity":120.0,"Location":"KAT/Stock/Zone (D)/Line 14/ZD-14-B06","Lot/Serial Number/Production Date":"2025-06-23 12:00:00","Lot/Serial Number/Expiration Date":"2026-06-23 12:00:00","Lot/Serial Number/Removal Date":"2026-05-18 12:00:00","Lot/Serial Number/Alert Date":"2026-06-23 12:00:00"},{"Product/Internal Reference":"30724637","Product/Name":"Spuds Craft Cooked Tomato Bruschetta (40-50g)","Product/Barcode":"","Financial Category":"Food","Available Quantity":0.0,"Quantity":0.0,"Location":"KAT/Stock/Zone (F)/Line 02/ZF-02-C06","Lot/Serial Number/Production Date":"2025-06-20 17:00:00","Lot/Serial Number/Expiration Date":"2025-12-17 16:00:00","Lot/Serial Number/Removal Date":"2025-11-29 16:00:00","Lot/Serial Number/Alert Date":"2025-12-17 16:00:00"},{"Product/Internal Reference":"2992763","Product/Name":"Sunshine Solid Tuna-Easy Open (200g)","Product/Barcode":"6223000717455","Financial Category":"Food Cupboard 2","Available Quantity":0.0,"Quantity":0.0,"Location":"KAT/Stock/Zone (C)/Line 11/ZC-11-C20","Lot/Serial Number/Production Date":"2024-10-01 14:00:00","Lot/Serial Number/Expiration Date":"2027-10-01 14:00:00","Lot/Serial Number/Removal Date":"2027-06-14 14:00:00","Lot/Serial Number/Alert Date":"2027-03-11 13:00:00"}]