[{"Product/Internal Reference":"249855","Product/Name":"Juhayna Rayeb Lite (220ml)","Product/Barcode":"6222014352447","Financial Category":"Yogurt","Available Quantity":0.0,"Quantity":0.0,"Location":"KAT/Stock","Lot/Serial Number/Production Date":"2025-07-14 15:00:00","Lot/Serial Number/Expiration Date":"2025-08-13 15:00:00","Lot/Serial Number/Removal Date":"2025-08-01 15:00:00","Lot/Serial Number/Alert Date":"2025-08-13 15:00:00"},{"Product/Internal Reference":"249870","Product/Name":"Juhayna Zabado Mango (440ml)","Product/Barcode":"6223000352649","Financial Category":"Yogurt","Available Quantity":0.0,"Quantity":0.0,"Location":"KAT/Stock","Lot/Serial Number/Production Date":"2025-07-15 15:00:00","Lot/Serial Number/Expiration Date":"2025-08-14 15:00:00","Lot/Serial Number/Removal Date":"2025-08-02 15:00:00","Lot/Serial Number/Alert Date":"2025-08-14 15:00:00"},{"Product/Internal Reference":"249859","Product/Name":"Juhayna Rayeb Green Tea & Lemon (440ml)","Product/Barcode":"6222014352225","Financial Category":"Yogurt","Available Quantity":528.0,"Quantity":528.0,"Location":"KAT/Stock","Lot/Serial Number/Production Date":"2025-07-15 15:00:00","Lot/Serial Number/Expiration Date":"2025-08-14 15:00:00","Lot/Serial Number/Removal Date":"2025-08-02 15:00:00","Lot/Serial Number/Alert Date":"2025-08-14 15:00:00"},{"Product/Internal Reference":"249857","Product/Name":"Juhayna Rayeb Light (440ml)","Product/Barcode":"6222014352249","Financial Category":"Yogurt","Available Quantity":0.0,"Quantity":0.0,"Location":"KAT/Stock","Lot/Serial Number/Production Date":"2025-07-15 15:00:00","Lot/Serial Number/Expiration Date":"2025-08-14 15:00:00","Lot/Serial Number/Removal Date":"2025-08-02 15:00:00","Lot/Serial Number/Alert Date":"2025-08-14 15:00:00"},{"Product/Internal Reference":"16611996","Product/Name":"Juhayna Yogurt Stirred Plain (105g)","Product/Barcode":"6222014300905","Financial Category":"Yogurt","Available Quantity":0.0,"Quantity":0.0,"Location":"KAT/Stock","Lot/Serial Number/Production Date":"2025-07-15 12:00:00","Lot/Serial Number/Expiration Date":"2025-08-14 12:00:00","Lot/Serial Number/Removal Date":"2025-08-02 12:00:00","Lot/Serial Number/Alert Date":"2025-08-14 12:00:00"}]