[{"Product/Internal Reference":"13384616","Product/Name":"Juhayna Pure Juice Orange And Carrot (235 ml)","Product/Barcode":"6222014332760","Financial Category":"Juice","Available Quantity":0.0,"Quantity":0.0,"Location":"KAT/Stock/Zone (C)/Line 04/ZC-04-A03","Lot/Serial Number/Production Date":"2025-06-30 15:00:00","Lot/Serial Number/Expiration Date":"2026-03-27 14:00:00","Lot/Serial Number/Removal Date":"2026-02-28 14:00:00","Lot/Serial Number/Alert Date":"2026-03-27 14:00:00"},{"Product/Internal Reference":"13384622","Product/Name":"Juhayna Pure Juice Red Grapes (1 L)","Product/Barcode":"6222014335600","Financial Category":"Juice","Available Quantity":0.0,"Quantity":0.0,"Location":"KAT/Stock/Zone (C)/Line 03/ZC-03-A05","Lot/Serial Number/Production Date":"2025-06-08 15:00:00","Lot/Serial Number/Expiration Date":"2026-03-05 14:00:00","Lot/Serial Number/Removal Date":"2026-02-06 14:00:00","Lot/Serial Number/Alert Date":"2026-03-05 14:00:00"},{"Product/Internal Reference":"13384623","Product/Name":"Juhayna Pure Juice Pomegranate (1L)","Product/Barcode":"6222014335655","Financial Category":"Juice","Available Quantity":0.0,"Quantity":0.0,"Location":"KAT/Stock/Zone (C)/Line 03/ZC-03-A05","Lot/Serial Number/Production Date":"2025-07-02 15:00:00","Lot/Serial Number/Expiration Date":"2026-03-29 14:00:00","Lot/Serial Number/Removal Date":"2026-03-02 14:00:00","Lot/Serial Number/Alert Date":"2026-03-29 14:00:00"},{"Product/Internal Reference":"22838465","Product/Name":"Juhayna Pina Colada Juice (1L)","Product/Barcode":"6222014301087","Financial Category":"Juice","Available Quantity":0.0,"Quantity":0.0,"Location":"KAT/Stock/Zone (C)/Line 04/ZC-04-C06","Lot/Serial Number/Production Date":"2025-07-11 15:00:00","Lot/Serial Number/Expiration Date":"2026-07-11 15:00:00","Lot/Serial Number/Removal Date":"2026-06-05 15:00:00","Lot/Serial Number/Alert Date":"2026-07-11 15:00:00"},{"Product/Internal Reference":"22838475","Product/Name":"Juhayna Pina Colada Juice (235ml)","Product/Barcode":"6222014301070","Financial Category":"Juice","Available Quantity":0.0,"Quantity":0.0,"Location":"KAT/Stock/Zone (C)/Line 04/ZC-04-A04","Lot/Serial Number/Production Date":"2025-06-13 15:00:00","Lot/Serial Number/Expiration Date":"2026-06-13 15:00:00","Lot/Serial Number/Removal Date":"2026-05-08 15:00:00","Lot/Serial Number/Alert Date":"2026-06-13 15:00:00"}]