[{"Product/Internal Reference":"30522543","Product/Name":"Katilo Light Feta Cheese (500g)","Product/Barcode":"","Financial Category":"Centralized Fresh","Available Quantity":216.0,"Quantity":216.0,"Location":"KAT/Stock","Lot/Serial Number/Production Date":"2025-07-23 13:00:00","Lot/Serial Number/Expiration Date":"2026-01-19 12:00:00","Lot/Serial Number/Removal Date":"2026-01-01 12:00:00","Lot/Serial Number/Alert Date":"2026-01-19 12:00:00"},{"Product/Internal Reference":"30524282","Product/Name":"Katilo Mesh Cheese (550g)","Product/Barcode":"","Financial Category":"Centralized Fresh","Available Quantity":156.0,"Quantity":156.0,"Location":"KAT/Stock","Lot/Serial Number/Production Date":"2025-07-21 13:00:00","Lot/Serial Number/Expiration Date":"2026-01-17 12:00:00","Lot/Serial Number/Removal Date":"2025-12-30 12:00:00","Lot/Serial Number/Alert Date":"2026-01-17 12:00:00"},{"Product/Internal Reference":"30523685","Product/Name":"Katilo Roumy Cheese Pure (300g)","Product/Barcode":"","Financial Category":"Centralized Fresh","Available Quantity":84.0,"Quantity":84.0,"Location":"KAT/Stock","Lot/Serial Number/Production Date":"2025-02-01 13:00:00","Lot/Serial Number/Expiration Date":"2026-02-01 13:00:00","Lot/Serial Number/Removal Date":"2025-12-27 13:00:00","Lot/Serial Number/Alert Date":"2026-02-01 13:00:00"},{"Product/Internal Reference":"30433886","Product/Name":"Katilo White Cheese Low Salt (500g)","Product/Barcode":"","Financial Category":"Centralized Fresh","Available Quantity":66.0,"Quantity":66.0,"Location":"KAT/Stock","Lot/Serial Number/Production Date":"2025-07-24 13:00:00","Lot/Serial Number/Expiration Date":"2025-08-23 13:00:00","Lot/Serial Number/Removal Date":"2025-08-11 13:00:00","Lot/Serial Number/Alert Date":"2025-08-23 13:00:00"},{"Product/Internal Reference":"30523728","Product/Name":"Katilo Vaccumed Roumy Cheese Slices (454g)","Product/Barcode":"","Financial Category":"Centralized Fresh","Available Quantity":24.0,"Quantity":24.0,"Location":"KAT/Stock","Lot/Serial Number/Production Date":"2025-06-01 13:00:00","Lot/Serial Number/Expiration Date":"2026-06-01 13:00:00","Lot/Serial Number/Removal Date":"2026-04-26 13:00:00","Lot/Serial Number/Alert Date":"2026-06-01 13:00:00"}]